codebangla/__init__.py
codebangla/__main__.py
codebangla/cli.py
codebangla/mappings.py
codebangla/py.typed
codebangla/tokenizer.py
codebangla/transpiler.py
codebangla/utils.py
codebangla-0.2.0.dist-info/licenses/LICENSE
codebangla-0.2.0.dist-info/METADATA
codebangla-0.2.0.dist-info/WHEEL
codebangla-0.2.0.dist-info/entry_points.txt
codebangla-0.2.0.dist-info/top_level.txt
codebangla-0.2.0.dist-info/RECORD
