Metadata-Version: 2.4
Name: codebangla
Version: 0.2.0
Summary: Advanced Python transpiler for writing Python code using Bangla keywords
Home-page: https://github.com/saky-semicolon/codebangla
Author: CodeBangla Team
Author-email: CodeBangla Team <team@codebangla.org>
Maintainer-email: CodeBangla Team <team@codebangla.org>
License-Expression: MIT
Project-URL: Homepage, https://github.com/saky-semicolon/codebangla
Project-URL: Documentation, https://codebangla.readthedocs.io
Project-URL: Repository, https://github.com/saky-semicolon/codebangla
Project-URL: Issues, https://github.com/saky-semicolon/codebangla/issues
Project-URL: Changelog, https://github.com/saky-semicolon/codebangla/blob/main/CHANGELOG.md
Keywords: bangla,python,transpiler,programming,education,localization
Classifier: Development Status :: 4 - Beta
Classifier: Intended Audience :: Developers
Classifier: Intended Audience :: Education
Classifier: Operating System :: OS Independent
Classifier: Programming Language :: Python :: 3
Classifier: Programming Language :: Python :: 3.8
Classifier: Programming Language :: Python :: 3.9
Classifier: Programming Language :: Python :: 3.10
Classifier: Programming Language :: Python :: 3.11
Classifier: Programming Language :: Python :: 3.12
Classifier: Topic :: Software Development :: Compilers
Classifier: Topic :: Software Development :: Localization
Classifier: Topic :: Education
Classifier: Topic :: Software Development :: Interpreters
Classifier: Natural Language :: Bengali
Classifier: Typing :: Typed
Requires-Python: >=3.8
License-File: LICENSE
Requires-Dist: click>=8.0.0
Provides-Extra: dev
Requires-Dist: pytest>=7.0.0; extra == "dev"
Requires-Dist: pytest-cov>=4.0.0; extra == "dev"
Requires-Dist: pytest-benchmark>=4.0.0; extra == "dev"
Requires-Dist: black>=22.0.0; extra == "dev"
Requires-Dist: flake8>=5.0.0; extra == "dev"
Requires-Dist: mypy>=1.0.0; extra == "dev"
Requires-Dist: isort>=5.0.0; extra == "dev"
Requires-Dist: pre-commit>=2.20.0; extra == "dev"
Provides-Extra: docs
Requires-Dist: sphinx>=5.0.0; extra == "docs"
Requires-Dist: sphinx-rtd-theme>=1.0.0; extra == "docs"
Requires-Dist: myst-parser>=0.18.0; extra == "docs"
Provides-Extra: test
Requires-Dist: pytest>=7.0.0; extra == "test"
Requires-Dist: pytest-cov>=4.0.0; extra == "test"
Requires-Dist: pytest-benchmark>=4.0.0; extra == "test"
Requires-Dist: coverage>=6.0.0; extra == "test"
Requires-Dist: tox>=4.0.0; extra == "test"
Provides-Extra: format
Requires-Dist: black>=22.0.0; extra == "format"
Requires-Dist: isort>=5.0.0; extra == "format"
Provides-Extra: lint
Requires-Dist: flake8>=5.0.0; extra == "lint"
Requires-Dist: mypy>=1.0.0; extra == "lint"
Provides-Extra: build
Requires-Dist: setuptools>=65.0.0; extra == "build"
Requires-Dist: wheel>=0.37.0; extra == "build"
Requires-Dist: twine>=4.0.0; extra == "build"
Provides-Extra: perf
Requires-Dist: chardet>=5.0.0; extra == "perf"
Requires-Dist: unicodedata2>=14.0.0; extra == "perf"
Provides-Extra: all
Requires-Dist: codebangla[build,dev,docs,format,lint,perf,test]; extra == "all"
Dynamic: author
Dynamic: home-page
Dynamic: license-file
Dynamic: requires-python
